mensajes/__init__.py
mensajes/adios/__init__.py
mensajes/adios/despedidas.py
mensajes/hola/__init__.py
mensajes/hola/saludos.py
tests/__init__.py
tests/tests_hola.py
Mensajes_pmontt-6.0.dist-info/LICENSE
Mensajes_pmontt-6.0.dist-info/METADATA
Mensajes_pmontt-6.0.dist-info/WHEEL
Mensajes_pmontt-6.0.dist-info/top_level.txt
Mensajes_pmontt-6.0.dist-info/RECORD
